django/__init__.py
django/__main__.py
django/shortcuts.py
django/apps/__init__.py
django/apps/config.py
django/apps/registry.py
django/conf/__init__.py
django/conf/global_settings.py
django/conf/locale/__init__.py
django/conf/urls/__init__.py
django/conf/urls/i18n.py
django/conf/urls/static.py
django/core/__init__.py
django/core/exceptions.py
django/core/paginator.py
django/core/signals.py
django/core/signing.py
django/core/validators.py
django/core/wsgi.py
django/core/cache/__init__.py
django/core/cache/utils.py
django/core/cache/backends/__init__.py
django/core/cache/backends/base.py
django/core/cache/backends/db.py
django/core/cache/backends/dummy.py
django/core/cache/backends/filebased.py
django/core/cache/backends/locmem.py
django/core/cache/backends/memcached.py
django/core/checks/__init__.py
django/core/checks/caches.py
django/core/checks/database.py
django/core/checks/messages.py
django/core/checks/model_checks.py
django/core/checks/registry.py
django/core/checks/templates.py
django/core/checks/translation.py
django/core/checks/urls.py
django/core/checks/compatibility/__init__.py
django/core/checks/security/__init__.py
django/core/checks/security/base.py
django/core/checks/security/csrf.py
django/core/checks/security/sessions.py
django/core/files/__init__.py
django/core/files/base.py
django/core/files/images.py
django/core/files/locks.py
django/core/files/move.py
django/core/files/storage.py
django/core/files/temp.py
django/core/files/uploadedfile.py
django/core/files/uploadhandler.py
django/core/files/utils.py
django/core/handlers/__init__.py
django/core/handlers/base.py
django/core/handlers/exception.py
django/core/handlers/wsgi.py
django/core/mail/__init__.py
django/core/mail/message.py
django/core/mail/utils.py
django/core/mail/backends/__init__.py
django/core/mail/backends/base.py
django/core/mail/backends/console.py
django/core/mail/backends/dummy.py
django/core/mail/backends/filebased.py
django/core/mail/backends/locmem.py
minidjango-2.2.dev20181110142024.dist-info/LICENSE
minidjango-2.2.dev20181110142024.dist-info/METADATA
minidjango-2.2.dev20181110142024.dist-info/WHEEL
minidjango-2.2.dev20181110142024.dist-info/entry_points.txt
minidjango-2.2.dev20181110142024.dist-info/top_level.txt
minidjango-2.2.dev20181110142024.dist-info/RECORD
